SystemEvent/__init__.py
SystemEvent-1.0.1.data/scripts/evt_clear
SystemEvent-1.0.1.data/scripts/evt_set
SystemEvent-1.0.1.data/scripts/evt_wait
SystemEvent-1.0.1.dist-info/DESCRIPTION.rst
SystemEvent-1.0.1.dist-info/METADATA
SystemEvent-1.0.1.dist-info/RECORD
SystemEvent-1.0.1.dist-info/WHEEL
SystemEvent-1.0.1.dist-info/metadata.json
SystemEvent-1.0.1.dist-info/top_level.txt
