Metadata-Version: 2.0
Name: SystemEvent
Version: 1.0.1
Summary: System-wide Event synchonization for posix (emulating the threading.Event api)
Home-page: UNKNOWN
Author: UNKNOWN
Author-email: UNKNOWN
License: MIT
Platform: UNKNOWN
Requires-Dist: posix-ipc (>=1.0.0)
